<?xml version="1.0" encoding="utf-8" ?>
<hibernate-mapping xmlns="urn:nhibernate-mapping-2.2">

  <class name="ProjectMgt.Model.WebService, ProjectMgt.Model" table="T_WebService">

    <id name="ID" column="ID" type="int">

      <generator class="identity" />
    </id>

    <property name ="WebServiceName" type ="String" />
    <property name ="WebServiceURI" type ="String" />
    <property name ="MethodName" type ="String" />
    <property name ="ArgArray" type ="String" />
    <property name ="Comment" type ="String" />
    <property name ="CreatorCode" type ="String" />
    <property name ="CreatorName" type ="String" />
    <property name ="CreateTime" type ="DateTime" />
  </class>
</hibernate-mapping>